Workbook

Sheet Consolidado de Calidad
B2: CONSOLIDADO DE EVALUACIÓN - ISO/IEC 25010
B3: Resumen general del porcentaje de calidad del software evaluado.
B5: Característica de Calidad | C5: Puntaje Máximo Posible | D5: Puntaje Obtenido | E5: Porcentaje de Calidad
B6: Adecuación Funcional | C6: =SUM('Adecuación Funcional'!$E$6:$E$8)*5 -> 75 | D6: =SUMPRODUCT('Adecuación Funcional'!$E$6:$E$8,'Adecuación Funcional'!$F$6:$F$8) -> 40 | E6: =IF(C6>0, D6/C6, 0) -> 0.53333333
B7: Eficiencia de Rendimiento | C7: =SUM('Eficiencia de Rendimiento'!$E$6:$E$8)*5 -> 75 | D7: =SUMPRODUCT('Eficiencia de Rendimiento'!$E$6:$E$8,'Eficiencia de Rendimiento'!$F$6:$F$8) -> 50 | E7: =IF(C7>0, D7/C7, 0) -> 0.66666667
B8: Compatibilidad | C8: =SUM(Compatibilidad!$E$6:$E$7)*5 -> 50 | D8: =SUMPRODUCT(Compatibilidad!$E$6:$E$7,Compatibilidad!$F$6:$F$7) -> 35 | E8: =IF(C8>0, D8/C8, 0) -> 0.7
B9: Usabilidad | C9: =SUM(Usabilidad!$E$6:$E$11)*5 -> 150 | D9: =SUMPRODUCT(Usabilidad!$E$6:$E$11,Usabilidad!$F$6:$F$11) -> 80 | E9: =IF(C9>0, D9/C9, 0) -> 0.53333333
B10: Fiabilidad | C10: =SUM(Fiabilidad!$E$6:$E$9)*5 -> 100 | D10: =SUMPRODUCT(Fiabilidad!$E$6:$E$9,Fiabilidad!$F$6:$F$9) -> 40 | E10: =IF(C10>0, D10/C10, 0) -> 0.4
B11: Seguridad | C11: =SUM(Seguridad!$E$6:$E$10)*5 -> 125 | D11: =SUMPRODUCT(Seguridad!$E$6:$E$10,Seguridad!$F$6:$F$10) -> 60 | E11: =IF(C11>0, D11/C11, 0) -> 0.48
B12: Mantenibilidad | C12: =SUM(Mantenibilidad!$E$6:$E$10)*5 -> 125 | D12: =SUMPRODUCT(Mantenibilidad!$E$6:$E$10,Mantenibilidad!$F$6:$F$10) -> 70 | E12: =IF(C12>0, D12/C12, 0) -> 0.56
B13: Portabilidad | C13: =SUM(Portabilidad!$E$6:$E$8)*5 -> 75 | D13: =SUMPRODUCT(Portabilidad!$E$6:$E$8,Portabilidad!$F$6:$F$8) -> 55 | E13: =IF(C13>0, D13/C13, 0) -> 0.73333333
B14: PORCENTAJE TOTAL DE CALIDAD DEL SOFTWARE | C14: =SUM(C6:C13) -> 775 | D14: =SUM(D6:D13) -> 430 | E14: =IF(C14>0, D14/C14, 0) -> 0.55483871

Sheet Adecuación Funcional
B2: MATRIZ DE EVALUACIÓN: ADECUACIÓN FUNCIONAL
B3: Instrucciones: Asigne un peso del 1 al 5 según la importancia del criterio, y califique de 0 a 5 el cumplimiento.
B5: ID | C5: Subcaracterística | D5: Criterio de Evaluación / Ejemplo | E5: Peso (1-5) | F5: Calificación (0-5) | G5: Observación / Evidencia
B6: FUNC_COMP_01 | C6: Completo funcional | D6: El sistema permite realizar todo el flujo de ventas desde el registro hasta la facturación sin omitir pasos críticos. | E6: 5 | F6: 2 | G6: Faltan funciones documentadas clave (exportación PDF, soft-delete, cotizaciones a ventas).
B7: FUNC_CORR_01 | C7: Corrección funcional | D7: Los cálculos de impuestos y descuentos en el carrito de compras son exactos según las reglas de negocio. | E7: 5 | F7: 2 | G7: La auditoría inicial identificó 15 no conformidades funcionales concretas en 15 RF evaluados.
B8: FUNC_PERT_01 | C8: Pertinencia funcional | D8: Las opciones del menú corresponden estrictamente a las tareas que el usuario necesita realizar en su rol. | E8: 5 | F8: 4 | G8: La interfaz presenta roles diferenciados, aunque el RBAC en backend reporta estado "Parcial".

Sheet Eficiencia de Rendimiento
B2: MATRIZ DE EVALUACIÓN: EFICIENCIA DE RENDIMIENTO
B3: Instrucciones: Asigne un peso del 1 al 5 según la importancia del criterio, y califique de 0 a 5 el cumplimiento.
B5: ID | C5: Subcaracterística | D5: Criterio de Evaluación / Ejemplo | E5: Peso (1-5) | F5: Calificación (0-5) | G5: Observación / Evidencia
B6: REND_TEMP_01 | C6: Comportamiento temporal | D6: El tiempo de respuesta del sistema al cargar la página de inicio es inferior a 2 segundos bajo carga normal. | E6: 5 | F6: 4 | G6: Rendimiento aceptable en desarrollo (NestJS/Vite operan con fluidez).
B7: REND_UTIL_01 | C7: Utilización de recursos | D7: El consumo de memoria RAM del servidor no supera el 60% durante la generación de reportes masivos. | E7: 5 | F7: 3 | G7: Por verificar en producción. No hay límites forzosos confirmados en consultas de bases de datos.
B8: REND_CAPA_01 | C8: Capacidad | D8: El sistema procesa correctamente 500 transacciones simultáneas sin degradar el servicio. | E8: 5 | F8: 3 | G8: Sin pruebas formales de estrés ni de carga (JMeter) realizadas hasta la fecha.

Sheet Compatibilidad
B2: MATRIZ DE EVALUACIÓN: COMPATIBILIDAD
B3: Instrucciones: Asigne un peso del 1 al 5 según la importancia del criterio, y califique de 0 a 5 el cumplimiento.
B5: ID | C5: Subcaracterística | D5: Criterio de Evaluación / Ejemplo | E5: Peso (1-5) | F5: Calificación (0-5) | G5: Observación / Evidencia
B6: COMP_COEX_01 | C6: Coexistencia | D6: La aplicación móvil funciona sin interferencias en dispositivos donde están instaladas apps de la competencia. | E6: 5 | F6: 4 | G6: El despliegue de backend aislado mediante Docker Compose facilita evitar conflictos de puertos.
B7: COMP_INTE_01 | C7: Interoperabilidad | D7: La API del sistema se integra y comparte datos correctamente con el módulo de contabilidad externo mediante JSON. | E7: 5 | F7: 3 | G7: El backend cuenta con API REST, pero no se evidencian integraciones activas o probadas con software externo contable.

Sheet Usabilidad
B2: MATRIZ DE EVALUACIÓN: USABILIDAD
B3: Instrucciones: Asigne un peso del 1 al 5 según la importancia del criterio, y califique de 0 a 5 el cumplimiento.
B5: ID | C5: Subcaracterística | D5: Criterio de Evaluación / Ejemplo | E5: Peso (1-5) | F5: Calificación (0-5) | G5: Observación / Evidencia
B6: USAB_RECO_01 | C6: Reconocimiento de adecuación | D6: El usuario identifica el propósito de la pantalla web en los primeros 5 segundos de visualización. | E6: 5 | F6: 4 | G6: Los dashboards y formularios presentan un propósito evidente.
B7: USAB_APRE_01 | C7: Aprendizaje | D7: Un usuario nuevo puede completar un registro de perfil sin necesidad de consultar un manual de ayuda. | E7: 5 | F7: 3 | G7: Faltan tooltips o guías interactivas para algunos flujos logísticos complejos (pedidos).
B8: USAB_OPER_01 | C8: Operabilidad | D8: El sistema ofrece atajos de teclado para las funciones más frecuentes, facilitando el trabajo continuo. | E8: 5 | F8: 2 | G8: No existen atajos de teclado implementados. Operabilidad netamente de ratón.
B9: USAB_PROT_01 | C9: Protección contra errores de usuario | D9: El sistema pide confirmación antes de eliminar permanentemente un registro de la base de datos. | E9: 5 | F9: 2 | G9: El borrado físico se permite sin protección suficiente; el soft-delete (borrado lógico) exigido no está implementado.
B10: USAB_ESTE_01 | C10: Estética de la interfaz de usuario | D10: El diseño visual mantiene una paleta de colores coherente y un espaciado que evita la fatiga visual. | E10: 5 | F10: 4 | G10: Diseño limpio y acorde, interfaz construida en Vite con estilos estandarizados.
B11: USAB_ACCE_01 | C11: Accesibilidad | D11: El sitio web cumple con las pautas WCAG, permitiendo la navegación con lectores de pantalla para personas visuales. | E11: 5 | F11: 1 | G11: Nula validación de accesibilidad WCAG o contrastes certificados.

Sheet Fiabilidad
B2: MATRIZ DE EVALUACIÓN: FIABILIDAD
B3: Instrucciones: Asigne un peso del 1 al 5 según la importancia del criterio, y califique de 0 a 5 el cumplimiento.
B5: ID | C5: Subcaracterística | D5: Criterio de Evaluación / Ejemplo | E5: Peso (1-5) | F5: Calificación (0-5) | G5: Observación / Evidencia
B6: FIAB_MADU_01 | C6: Madurez | D6: El sistema opera de forma continua en producción sin presentar caídas imprevistas durante la última semana. | E6: 5 | F6: 2 | G6: Proyecto inmaduro, en primera iteración de QA. No está certificado para producción continua.
B7: FIAB_DISP_01 | C7: Disponibilidad | D7: La plataforma está operativa y accesible para los usuarios el 99.9% del tiempo contratado en el mes. | E7: 5 | F7: 3 | G7: La contenedorización otorga cierta estabilidad, pero no se ha medido el SLA en entorno real.
B8: FIAB_TOLE_01 | C8: Tolerancia a fallos | D8: Si la conexión con la base de datos principal falla, el sistema conmuta automáticamente a la réplica de lectura. | E8: 5 | F8: 1 | G8: No existe configuración de clúster ni réplica de lectura activa. Sistema de base de datos único.
B9: FIAB_RECU_01 | C9: Capacidad de recuperación | D9: Tras un corte de energía, el sistema restaura el estado de los datos al último punto de control guardado. | E9: 5 | F9: 2 | G9: Existen volúmenes Docker persistentes, pero no hay evidencia de rutinas de backup automatizadas.

Sheet Seguridad
B2: MATRIZ DE EVALUACIÓN: SEGURIDAD
B3: Instrucciones: Asigne un peso del 1 al 5 según la importancia del criterio, y califique de 0 a 5 el cumplimiento.
B5: ID | C5: Subcaracterística | D5: Criterio de Evaluación / Ejemplo | E5: Peso (1-5) | F5: Calificación (0-5) | G5: Observación / Evidencia
B6: SEGU_CONF_01 | C6: Confidencialidad | D6: Las contraseñas de los usuarios están encriptadas con un algoritmo robusto (ej. bcrypt) en la base de datos. | E6: 5 | F6: 1 | G6: Falla Crítica: Exposición directa de credenciales, secretos `.env` y clave secreta JWT expuesta en el repositorio.
B7: SEGU_INTE_01 | C7: Integridad | D7: El sistema evita modificaciones no autorizadas en los datos mediante validaciones en el servidor (backend). | E7: 5 | F7: 3 | G7: Backend con validaciones, pero existen deficiencias lógicas (ej. saltos de estado logísticos no controlados).
B8: SEGU_NORE_01 | C8: No repudio | D8: Cada transacción financiera registra de forma inalterable el ID del usuario, fecha y hora en el log de auditoría. | E8: 5 | F8: 3 | G8: Trazabilidad presente, pero el sistema global de auditoría requiere refuerzo para inmutabilidad completa.
B9: SEGU_RESP_01 | C9: Responsabilidad | D9: El sistema registra de manera clara qué acciones ejecutó cada administrador para poder auditar incidentes. | E9: 5 | F9: 3 | G9: Se registra el responsable, aunque las acciones administrativas sobre permisos no se auditan a detalle profundo.
B10: SEGU_AUTE_01 | C10: Autenticidad | D10: El sistema valida tokens digitales (JWT) firmados para confirmar que las peticiones provienen de usuarios válidos. | E10: 5 | F10: 2 | G10: JWT implementado de manera estándar, pero el `JWT_SECRET` hardcodeado (fallback) vulnera gravemente la protección.

Sheet Mantenibilidad
B2: MATRIZ DE EVALUACIÓN: MANTENIBILIDAD
B3: Instrucciones: Asigne un peso del 1 al 5 según la importancia del criterio, y califique de 0 a 5 el cumplimiento.
B5: ID | C5: Subcaracterística | D5: Criterio de Evaluación / Ejemplo | E5: Peso (1-5) | F5: Calificación (0-5) | G5: Observación / Evidencia
B6: MANT_MODU_01 | C6: Modularidad | D6: Un cambio en el módulo de facturación no afecta ni altera el funcionamiento del módulo de inventarios. | E6: 5 | F6: 4 | G6: El framework NestJS proporciona una estructura nativa de módulos aislados de buena calidad.
B7: MANT_REUS_01 | C7: Reusabilidad | D7: El componente visual de calendario se utiliza en múltiples formularios del sistema sin duplicar código. | E7: 5 | F7: 3 | G7: Uso aceptable de componentes, aunque existen porciones de lógica acopladas.
B8: MANT_ANAL_01 | C8: Analizabilidad | D8: Los logs de error detallan la línea de código y el archivo exacto donde ocurrió una excepción para su diagnóstico. | E8: 5 | F8: 2 | G8: Sistema de logs básico; falta integración de SonarQube para deuda técnica y una herramienta APM sólida.
B9: MANT_MODI_01 | C9: Modificabilidad | D9: Agregar un nuevo campo al formulario de registro requiere modificaciones mínimas en la base de datos y backend. | E9: 5 | F9: 4 | G9: El uso del ORM Prisma facilita la gestión de esquemas y las migraciones de forma ágil.
B10: MANT_PRUE_01 | C10: Capacidad de prueba | D10: El código fuente cuenta con pruebas unitarias automatizadas que cubren al menos el 80% de las funciones. | E10: 5 | F10: 1 | G10: Riesgo extremo: Ausencia de cobertura (1 archivo Jest en backend, 0 en frontend, sin pruebas UI/Cypress).

Sheet Portabilidad
B2: MATRIZ DE EVALUACIÓN: PORTABILIDAD
B3: Instrucciones: Asigne un peso del 1 al 5 según la importancia del criterio, y califique de 0 a 5 el cumplimiento.
B5: ID | C5: Subcaracterística | D5: Criterio de Evaluación / Ejemplo | E5: Peso (1-5) | F5: Calificación (0-5) | G5: Observación / Evidencia
B6: PORT_ADAP_01 | C6: Adaptabilidad | D6: La aplicación web se adapta y visualiza correctamente en pantallas de laptops, tablets y smartphones. | E6: 5 | F6: 3 | G6: Interfaces web son responsive, pero la versión móvil opera con un frontend completamente separado (React Native).
B7: PORT_INST_01 | C7: Facilidad de instalación | D7: El sistema se puede desplegar en un servidor nuevo en menos de una hora usando contenedores Docker. | E7: 5 | F7: 5 | G7: Excelente implementación de `docker-compose.yml`, que permite iniciar DB, Frontend y Backend casi instantáneamente.
B8: PORT_SUST_01 | C8: Facilidad de sustitución | D8: La aplicación puede reemplazar al software anterior importando de forma directa la base de datos vieja. | E8: 5 | F8: 3 | G8: Factible, aunque requeriría mapeo de datos manual debido a las llaves primarias estrictas en Prisma.

Sheet Banco de Preguntas
B2: BANCO DE PREGUNTAS PARA APRENDICES
B3: Cuestionario guía para auditorías de calidad de software basadas en ISO 25010.
B5: N° | C5: Pregunta de Evaluación | D5: Característica Asociada | E5: Subcaracterística Asociada
B6: 1 | C6: ¿El sistema incluye todas las funciones especificadas en los requisitos iniciales? | D6: Adecuación Funcional | E6: Completo funcional
B7: 2 | C7: ¿El software arroja resultados matemáticos correctos en los reportes contables? | D7: Adecuación Funcional | E7: Corrección funcional
B8: 3 | C8: ¿Las opciones visibles ayudan directamente al usuario a cumplir sus metas de negocio? | D8: Adecuación Funcional | E8: Pertinencia funcional
B9: 4 | C9: ¿La búsqueda de productos tarda menos de un segundo en mostrar resultados? | D9: Eficiencia de Rendimiento | E9: Comportamiento temporal
B10: 5 | C10: ¿El sistema libera la memoria RAM después de cerrar un reporte complejo? | D10: Eficiencia de Rendimiento | E10: Utilización de recursos
B11: 6 | C11: ¿Soporta el aumento repentino de usuarios en fechas de alta demanda (Black Friday)? | D11: Eficiencia de Rendimiento | E11: Capacidad
B12: 7 | C12: ¿Puede ejecutarse al mismo tiempo que el antivirus sin ralentizar el equipo? | D12: Compatibilidad | E12: Coexistencia
B13: 8 | C13: ¿Los datos exportados en Excel se abren correctamente en otras suites de oficina? | D13: Compatibilidad | E13: Interoperabilidad
B14: 9 | C14: ¿Los iconos utilizados representan claramente la acción que van a realizar? | D14: Usabilidad | E14: Reconocimiento de adecuación
B15: 10 | C15: ¿Los mensajes de bienvenida guían intuitivamente al usuario nuevo? | D15: Usabilidad | E15: Aprendizaje
B16: 11 | C16: ¿Es fácil navegar por el sitio utilizando únicamente el teclado? | D16: Usabilidad | E16: Operabilidad
B17: 12 | C17: ¿El sistema previene que se envíe un formulario vacío resaltando los campos? | D17: Usabilidad | E17: Protección contra errores de usuario
... B36: 31 | C36: ¿Es posible migrar los datos al nuevo sistema sin pérdida de información histórica? | D36: Portabilidad | E36: Facilidad de sustitución
